arcam/fmj/__init__.py
arcam/fmj/client.py
arcam/fmj/console.py
arcam/fmj/py.typed
arcam/fmj/server.py
arcam/fmj/state.py
arcam/fmj/utils.py
arcam_fmj-1.8.2.dist-info/licenses/LICENSE.txt
arcam_fmj-1.8.2.dist-info/METADATA
arcam_fmj-1.8.2.dist-info/WHEEL
arcam_fmj-1.8.2.dist-info/entry_points.txt
arcam_fmj-1.8.2.dist-info/top_level.txt
arcam_fmj-1.8.2.dist-info/RECORD
