Metadata-Version: 2.4
Name: arcam-fmj
Version: 1.8.2
Summary: A python library for speaking to Arcam receivers
Home-page: https://github.com/elupus/arcam_fmj
Author: Joakim Plate
License: MIT
Classifier: License :: OSI Approved :: MIT License
Classifier: Development Status :: 4 - Beta
Classifier: Environment :: Console
Classifier: Environment :: Plugins
Classifier: Framework :: AsyncIO
Requires-Python: >=3.8
License-File: LICENSE.txt
Requires-Dist: attrs>18.1
Provides-Extra: tests
Requires-Dist: pytest>3.6.4; extra == "tests"
Requires-Dist: pytest-asyncio==0.21.2; extra == "tests"
Requires-Dist: pytest-aiohttp>=1.0.0; extra == "tests"
Requires-Dist: pytest-cov>=3.0.0; extra == "tests"
Requires-Dist: coveralls; extra == "tests"
Requires-Dist: pytest-mock; extra == "tests"
Requires-Dist: aiohttp; extra == "tests"
Requires-Dist: defusedxml; extra == "tests"
Dynamic: author
Dynamic: classifier
Dynamic: description
Dynamic: description-content-type
Dynamic: home-page
Dynamic: license
Dynamic: license-file
Dynamic: provides-extra
Dynamic: requires-dist
Dynamic: requires-python
Dynamic: summary
